{
  "source": "PSKReporter",
  "generated_at": "2026-07-22T07:32:23.810940+00:00",
  "status": "partial",
  "scope": "Observed HF reports attributable to Península, Baleares or Canarias",
  "classification_method": "Spanish call area with locator cross-check",
  "query_fields": [
    "IL",
    "IM",
    "IN",
    "JM",
    "JN"
  ],
  "raw_report_count": 6763,
  "accepted_report_count": 4625,
  "regions": {
    "peninsula": {
      "status": "ok",
      "report_count": 2975,
      "bands": {
        "80m": {
          "report_count": 1,
          "station_count": 2,
          "route_count": 1,
          "modes": {
            "WSPR": 1
          },
          "directions": {
            "transmitted_from_region": 1
          },
          "distance_km": {
            "minimum": 1457.6,
            "median": 1457.6,
            "maximum": 1457.6
          },
          "latest_observation_utc": "2026-07-22T07:30:00+00:00"
        },
        "60m": {
          "report_count": 2,
          "station_count": 3,
          "route_count": 2,
          "modes": {
            "WSPR": 2
          },
          "directions": {
            "interregional": 2
          },
          "distance_km": {
            "minimum": 1704.8,
            "median": 1707.0,
            "maximum": 1709.3
          },
          "latest_observation_utc": "2026-07-22T07:26:00+00:00"
        },
        "40m": {
          "report_count": 397,
          "station_count": 193,
          "route_count": 397,
          "modes": {
            "CW": 3,
            "FT8": 376,
            "JS8": 6,
            "VARAC": 1,
            "WSPR": 11
          },
          "directions": {
            "internal": 39,
            "interregional": 24,
            "received_in_region": 71,
            "transmitted_from_region": 263
          },
          "distance_km": {
            "minimum": 16.9,
            "median": 1470.3,
            "maximum": 19863.9
          },
          "latest_observation_utc": "2026-07-22T07:32:15+00:00"
        },
        "30m": {
          "report_count": 507,
          "station_count": 266,
          "route_count": 507,
          "modes": {
            "FT4": 1,
            "FT8": 486,
            "WSPR": 20
          },
          "directions": {
            "internal": 30,
            "interregional": 20,
            "received_in_region": 124,
            "transmitted_from_region": 333
          },
          "distance_km": {
            "minimum": 43.6,
            "median": 1655.0,
            "maximum": 19692.3
          },
          "latest_observation_utc": "2026-07-22T07:32:15+00:00"
        },
        "20m": {
          "report_count": 1342,
          "station_count": 602,
          "route_count": 1342,
          "modes": {
            "CW": 4,
            "FT2": 2,
            "FT4": 119,
            "FT8": 1178,
            "MFSK": 2,
            "VARAC": 3,
            "WSPR": 34
          },
          "directions": {
            "internal": 59,
            "interregional": 44,
            "received_in_region": 536,
            "transmitted_from_region": 703
          },
          "distance_km": {
            "minimum": 0.0,
            "median": 1861.1,
            "maximum": 19755.6
          },
          "latest_observation_utc": "2026-07-22T07:32:22+00:00"
        },
        "17m": {
          "report_count": 219,
          "station_count": 135,
          "route_count": 219,
          "modes": {
            "FT8": 209,
            "WSPR": 10
          },
          "directions": {
            "internal": 12,
            "interregional": 14,
            "received_in_region": 75,
            "transmitted_from_region": 118
          },
          "distance_km": {
            "minimum": 182.2,
            "median": 1778.3,
            "maximum": 18858.4
          },
          "latest_observation_utc": "2026-07-22T07:32:15+00:00"
        },
        "15m": {
          "report_count": 352,
          "station_count": 177,
          "route_count": 351,
          "modes": {
            "CW": 1,
            "FT4": 36,
            "FT8": 310,
            "WSPR": 5
          },
          "directions": {
            "internal": 19,
            "interregional": 11,
            "received_in_region": 212,
            "transmitted_from_region": 110
          },
          "distance_km": {
            "minimum": 186.5,
            "median": 1517.3,
            "maximum": 11019.8
          },
          "latest_observation_utc": "2026-07-22T07:32:15+00:00"
        },
        "12m": {
          "report_count": 25,
          "station_count": 20,
          "route_count": 25,
          "modes": {
            "FT8": 24,
            "WSPR": 1
          },
          "directions": {
            "interregional": 5,
            "received_in_region": 19,
            "transmitted_from_region": 1
          },
          "distance_km": {
            "minimum": 873.6,
            "median": 1925.6,
            "maximum": 4207.1
          },
          "latest_observation_utc": "2026-07-22T07:31:00+00:00"
        },
        "10m": {
          "report_count": 130,
          "station_count": 85,
          "route_count": 130,
          "modes": {
            "FT8": 128,
            "WSPR": 2
          },
          "directions": {
            "internal": 6,
            "interregional": 5,
            "received_in_region": 81,
            "transmitted_from_region": 38
          },
          "distance_km": {
            "minimum": 338.0,
            "median": 1667.8,
            "maximum": 6258.6
          },
          "latest_observation_utc": "2026-07-22T07:32:14+00:00"
        }
      },
      "consultation_reliability_pct": 80,
      "evidence_weight_recommendation": 2
    },
    "baleares": {
      "status": "ok",
      "report_count": 55,
      "bands": {
        "80m": {
          "report_count": 1,
          "station_count": 2,
          "route_count": 1,
          "modes": {
            "WSPR": 1
          },
          "directions": {
            "transmitted_from_region": 1
          },
          "distance_km": {
            "minimum": 1309.4,
            "median": 1309.4,
            "maximum": 1309.4
          },
          "latest_observation_utc": "2026-07-22T07:28:00+00:00"
        },
        "40m": {
          "report_count": 8,
          "station_count": 10,
          "route_count": 8,
          "modes": {
            "WSPR": 8
          },
          "directions": {
            "interregional": 1,
            "transmitted_from_region": 7
          },
          "distance_km": {
            "minimum": 723.9,
            "median": 1275.2,
            "maximum": 1957.8
          },
          "latest_observation_utc": "2026-07-22T07:30:00+00:00"
        },
        "20m": {
          "report_count": 9,
          "station_count": 10,
          "route_count": 9,
          "modes": {
            "WSPR": 9
          },
          "directions": {
            "transmitted_from_region": 9
          },
          "distance_km": {
            "minimum": 730.2,
            "median": 1289.0,
            "maximum": 6208.9
          },
          "latest_observation_utc": "2026-07-22T07:30:00+00:00"
        },
        "17m": {
          "report_count": 3,
          "station_count": 4,
          "route_count": 3,
          "modes": {
            "WSPR": 3
          },
          "directions": {
            "interregional": 1,
            "transmitted_from_region": 2
          },
          "distance_km": {
            "minimum": 889.1,
            "median": 1283.5,
            "maximum": 1939.0
          },
          "latest_observation_utc": "2026-07-22T07:28:00+00:00"
        },
        "15m": {
          "report_count": 3,
          "station_count": 4,
          "route_count": 3,
          "modes": {
            "WSPR": 3
          },
          "directions": {
            "interregional": 1,
            "transmitted_from_region": 2
          },
          "distance_km": {
            "minimum": 724.9,
            "median": 1315.8,
            "maximum": 1939.0
          },
          "latest_observation_utc": "2026-07-22T07:30:00+00:00"
        },
        "12m": {
          "report_count": 30,
          "station_count": 29,
          "route_count": 30,
          "modes": {
            "FT8": 30
          },
          "directions": {
            "interregional": 6,
            "received_in_region": 10,
            "transmitted_from_region": 14
          },
          "distance_km": {
            "minimum": 757.6,
            "median": 1366.6,
            "maximum": 3987.6
          },
          "latest_observation_utc": "2026-07-22T07:29:41+00:00"
        },
        "10m": {
          "report_count": 1,
          "station_count": 2,
          "route_count": 1,
          "modes": {
            "WSPR": 1
          },
          "directions": {
            "transmitted_from_region": 1
          },
          "distance_km": {
            "minimum": 1399.4,
            "median": 1399.4,
            "maximum": 1399.4
          },
          "latest_observation_utc": "2026-07-22T07:30:00+00:00"
        }
      },
      "consultation_reliability_pct": 80,
      "evidence_weight_recommendation": 2
    },
    "canarias": {
      "status": "ok",
      "report_count": 1725,
      "bands": {
        "60m": {
          "report_count": 2,
          "station_count": 3,
          "route_count": 2,
          "modes": {
            "WSPR": 2
          },
          "directions": {
            "interregional": 2
          },
          "distance_km": {
            "minimum": 1704.8,
            "median": 1707.0,
            "maximum": 1709.3
          },
          "latest_observation_utc": "2026-07-22T07:26:00+00:00"
        },
        "40m": {
          "report_count": 224,
          "station_count": 174,
          "route_count": 224,
          "modes": {
            "FT8": 192,
            "WSPR": 32
          },
          "directions": {
            "internal": 1,
            "interregional": 25,
            "received_in_region": 102,
            "transmitted_from_region": 96
          },
          "distance_km": {
            "minimum": 268.9,
            "median": 5565.2,
            "maximum": 18978.2
          },
          "latest_observation_utc": "2026-07-22T07:31:45+00:00"
        },
        "30m": {
          "report_count": 203,
          "station_count": 119,
          "route_count": 203,
          "modes": {
            "FT8": 146,
            "WSPR": 57
          },
          "directions": {
            "interregional": 20,
            "received_in_region": 182,
            "transmitted_from_region": 1
          },
          "distance_km": {
            "minimum": 1098.1,
            "median": 3231.0,
            "maximum": 18226.9
          },
          "latest_observation_utc": "2026-07-22T07:32:00+00:00"
        },
        "20m": {
          "report_count": 1010,
          "station_count": 698,
          "route_count": 1008,
          "modes": {
            "FT2": 4,
            "FT4": 54,
            "FT8": 880,
            "WSPR": 72
          },
          "directions": {
            "internal": 1,
            "interregional": 44,
            "received_in_region": 392,
            "transmitted_from_region": 573
          },
          "distance_km": {
            "minimum": 242.8,
            "median": 3906.4,
            "maximum": 19183.6
          },
          "latest_observation_utc": "2026-07-22T07:32:00+00:00"
        },
        "17m": {
          "report_count": 104,
          "station_count": 67,
          "route_count": 104,
          "modes": {
            "FT8": 84,
            "WSPR": 20
          },
          "directions": {
            "interregional": 15,
            "received_in_region": 89
          },
          "distance_km": {
            "minimum": 1150.8,
            "median": 3211.6,
            "maximum": 18709.4
          },
          "latest_observation_utc": "2026-07-22T07:31:45+00:00"
        },
        "15m": {
          "report_count": 138,
          "station_count": 92,
          "route_count": 138,
          "modes": {
            "FT4": 2,
            "FT8": 130,
            "WSPR": 6
          },
          "directions": {
            "interregional": 12,
            "received_in_region": 126
          },
          "distance_km": {
            "minimum": 1727.5,
            "median": 3678.8,
            "maximum": 18452.9
          },
          "latest_observation_utc": "2026-07-22T07:32:00+00:00"
        },
        "12m": {
          "report_count": 22,
          "station_count": 16,
          "route_count": 22,
          "modes": {
            "FT8": 22
          },
          "directions": {
            "interregional": 3,
            "received_in_region": 19
          },
          "distance_km": {
            "minimum": 1871.2,
            "median": 2916.3,
            "maximum": 5041.9
          },
          "latest_observation_utc": "2026-07-22T07:29:15+00:00"
        },
        "10m": {
          "report_count": 22,
          "station_count": 18,
          "route_count": 22,
          "modes": {
            "FT8": 21,
            "WSPR": 1
          },
          "directions": {
            "interregional": 5,
            "received_in_region": 17
          },
          "distance_km": {
            "minimum": 1605.9,
            "median": 2971.1,
            "maximum": 6756.3
          },
          "latest_observation_utc": "2026-07-22T07:31:45+00:00"
        }
      },
      "consultation_reliability_pct": 80,
      "evidence_weight_recommendation": 2
    }
  },
  "national_fallback": {
    "status": "available",
    "report_count": 4625,
    "bands": {
      "80m": {
        "report_count": 2,
        "station_count": 4,
        "route_count": 2,
        "modes": {
          "WSPR": 2
        },
        "directions": {
          "transmitted_from_region": 2
        },
        "distance_km": {
          "minimum": 1309.4,
          "median": 1383.5,
          "maximum": 1457.6
        },
        "latest_observation_utc": "2026-07-22T07:30:00+00:00"
      },
      "60m": {
        "report_count": 2,
        "station_count": 3,
        "route_count": 2,
        "modes": {
          "WSPR": 2
        },
        "directions": {
          "interregional": 2
        },
        "distance_km": {
          "minimum": 1704.8,
          "median": 1707.0,
          "maximum": 1709.3
        },
        "latest_observation_utc": "2026-07-22T07:26:00+00:00"
      },
      "40m": {
        "report_count": 604,
        "station_count": 295,
        "route_count": 604,
        "modes": {
          "CW": 3,
          "FT8": 549,
          "JS8": 6,
          "VARAC": 1,
          "WSPR": 45
        },
        "directions": {
          "internal": 40,
          "interregional": 25,
          "received_in_region": 173,
          "transmitted_from_region": 366
        },
        "distance_km": {
          "minimum": 16.9,
          "median": 1808.3,
          "maximum": 19863.9
        },
        "latest_observation_utc": "2026-07-22T07:32:15+00:00"
      },
      "30m": {
        "report_count": 690,
        "station_count": 320,
        "route_count": 690,
        "modes": {
          "FT4": 1,
          "FT8": 618,
          "WSPR": 71
        },
        "directions": {
          "internal": 30,
          "interregional": 20,
          "received_in_region": 306,
          "transmitted_from_region": 334
        },
        "distance_km": {
          "minimum": 43.6,
          "median": 2085.8,
          "maximum": 19692.3
        },
        "latest_observation_utc": "2026-07-22T07:32:15+00:00"
      },
      "20m": {
        "report_count": 2317,
        "station_count": 936,
        "route_count": 2315,
        "modes": {
          "CW": 4,
          "FT2": 6,
          "FT4": 167,
          "FT8": 2023,
          "MFSK": 2,
          "VARAC": 3,
          "WSPR": 112
        },
        "directions": {
          "internal": 60,
          "interregional": 44,
          "received_in_region": 928,
          "transmitted_from_region": 1285
        },
        "distance_km": {
          "minimum": 0.0,
          "median": 3019.6,
          "maximum": 19755.6
        },
        "latest_observation_utc": "2026-07-22T07:32:22+00:00"
      },
      "17m": {
        "report_count": 311,
        "station_count": 165,
        "route_count": 311,
        "modes": {
          "FT8": 282,
          "WSPR": 29
        },
        "directions": {
          "internal": 12,
          "interregional": 15,
          "received_in_region": 164,
          "transmitted_from_region": 120
        },
        "distance_km": {
          "minimum": 182.2,
          "median": 2314.3,
          "maximum": 18858.4
        },
        "latest_observation_utc": "2026-07-22T07:32:15+00:00"
      },
      "15m": {
        "report_count": 481,
        "station_count": 210,
        "route_count": 480,
        "modes": {
          "CW": 1,
          "FT4": 36,
          "FT8": 431,
          "WSPR": 13
        },
        "directions": {
          "internal": 19,
          "interregional": 12,
          "received_in_region": 338,
          "transmitted_from_region": 112
        },
        "distance_km": {
          "minimum": 186.5,
          "median": 1852.5,
          "maximum": 18452.9
        },
        "latest_observation_utc": "2026-07-22T07:32:15+00:00"
      },
      "12m": {
        "report_count": 70,
        "station_count": 41,
        "route_count": 70,
        "modes": {
          "FT8": 69,
          "WSPR": 1
        },
        "directions": {
          "interregional": 7,
          "received_in_region": 48,
          "transmitted_from_region": 15
        },
        "distance_km": {
          "minimum": 757.6,
          "median": 1951.2,
          "maximum": 5041.9
        },
        "latest_observation_utc": "2026-07-22T07:31:00+00:00"
      },
      "10m": {
        "report_count": 148,
        "station_count": 89,
        "route_count": 148,
        "modes": {
          "FT8": 144,
          "WSPR": 4
        },
        "directions": {
          "internal": 6,
          "interregional": 5,
          "received_in_region": 98,
          "transmitted_from_region": 39
        },
        "distance_km": {
          "minimum": 338.0,
          "median": 1719.5,
          "maximum": 6756.3
        },
        "latest_observation_utc": "2026-07-22T07:32:14+00:00"
      }
    },
    "use_only_when_regional_attribution_is_insufficient": true
  }
}
