{
  "schema_version": "1.2",
  "source": "Reverse Beacon Network",
  "generated_at": "2026-07-24T01:05:29.067866+00:00",
  "status": "ok",
  "transport": "telnet",
  "scope": "live spots only",
  "bands": {
    "20m": 14,
    "80m": 6,
    "40m": 19,
    "17m": 9,
    "15m": 6,
    "160m": 1,
    "10m": 3
  },
  "spots": [
    {
      "raw": "DX de NG7M-#:   14080.00  N5TLH          FT4  -12 dB          CQ      0105Z",
      "receiver_callsign": "NG7M-#",
      "heard_callsign": "N5TLH",
      "receiver_region": null,
      "frequency_mhz": 14.08,
      "band": "20m"
    },
    {
      "raw": "DX de DL8LAS-#:  3573.00  W3DIY          FT8   -1 dB  FM19    CQ      0105Z",
      "receiver_callsign": "DL8LAS-#",
      "heard_callsign": "W3DIY",
      "receiver_region": null,
      "frequency_mhz": 3.573,
      "band": "80m"
    },
    {
      "raw": "DX de DL8LAS-#: 10136.00  IK6DLK         FT8    7 dB  JN63    CQ      0105Z",
      "receiver_callsign": "DL8LAS-#",
      "heard_callsign": "JN63",
      "receiver_region": null,
      "frequency_mhz": 7.0,
      "band": "40m"
    },
    {
      "raw": "DX de DL8LAS-#: 18100.00  IZ3ATV         FT8   -9 dB  JN55    CQ      0105Z",
      "receiver_callsign": "DL8LAS-#",
      "heard_callsign": "IZ3ATV",
      "receiver_region": null,
      "frequency_mhz": 18.1,
      "band": "17m"
    },
    {
      "raw": "DX de DL8LAS-#: 18100.00  PT2TD          FT8  -12 dB          CQ      0105Z",
      "receiver_callsign": "DL8LAS-#",
      "heard_callsign": "PT2TD",
      "receiver_region": null,
      "frequency_mhz": 18.1,
      "band": "17m"
    },
    {
      "raw": "DX de DL8LAS-#:  7074.00  W4DXM          FT8   16 dB  EL97    CQ      0105Z",
      "receiver_callsign": "DL8LAS-#",
      "heard_callsign": "W4DXM",
      "receiver_region": null,
      "frequency_mhz": 7.074,
      "band": "40m"
    },
    {
      "raw": "DX de DL8LAS-#:  7074.00  EA1IOK         FT8    1 dB  IN62    CQ      0105Z",
      "receiver_callsign": "DL8LAS-#",
      "heard_callsign": "EA1IOK",
      "receiver_region": null,
      "frequency_mhz": 7.074,
      "band": "40m"
    },
    {
      "raw": "DX de DL8LAS-#:  7074.00  KN4WJY         FT8   -8 dB          CQ      0105Z",
      "receiver_callsign": "DL8LAS-#",
      "heard_callsign": "KN4WJY",
      "receiver_region": null,
      "frequency_mhz": 7.074,
      "band": "40m"
    },
    {
      "raw": "DX de DL8LAS-#:  7074.00  F4BYA          FT8   -6 dB  JN19    CQ      0105Z",
      "receiver_callsign": "DL8LAS-#",
      "heard_callsign": "F4BYA",
      "receiver_region": null,
      "frequency_mhz": 7.074,
      "band": "40m"
    },
    {
      "raw": "DX de DL8LAS-#:  7074.00  9A4ZM          FT8  -13 dB  JN86    CQ      0105Z",
      "receiver_callsign": "DL8LAS-#",
      "heard_callsign": "9A4ZM",
      "receiver_region": null,
      "frequency_mhz": 7.074,
      "band": "40m"
    },
    {
      "raw": "DX de DL8LAS-#:  7074.00  W5LD           FT8  -10 dB          CQ      0105Z",
      "receiver_callsign": "DL8LAS-#",
      "heard_callsign": "W5LD",
      "receiver_region": null,
      "frequency_mhz": 7.074,
      "band": "40m"
    },
    {
      "raw": "DX de DL8LAS-#:  7074.00  RA3TKS         FT8    5 dB          CQ      0105Z",
      "receiver_callsign": "DL8LAS-#",
      "heard_callsign": "RA3TKS",
      "receiver_region": null,
      "frequency_mhz": 7.074,
      "band": "40m"
    },
    {
      "raw": "DX de DL8LAS-#:  7074.00  RQ6B           FT8   -1 dB  KN94    CQ      0105Z",
      "receiver_callsign": "DL8LAS-#",
      "heard_callsign": "RQ6B",
      "receiver_region": null,
      "frequency_mhz": 7.074,
      "band": "40m"
    },
    {
      "raw": "DX de K9IMM-#:  18100.00  VA6MNT         FT8   12 dB          CQ      0105Z",
      "receiver_callsign": "K9IMM-#",
      "heard_callsign": "VA6MNT",
      "receiver_region": null,
      "frequency_mhz": 18.1,
      "band": "17m"
    },
    {
      "raw": "DX de K9IMM-#:  18100.00  N5UG           FT8   22 dB  EM16    CQ      0105Z",
      "receiver_callsign": "K9IMM-#",
      "heard_callsign": "N5UG",
      "receiver_region": null,
      "frequency_mhz": 18.1,
      "band": "17m"
    },
    {
      "raw": "DX de K9IMM-#:  21074.00  KJ5CYH         FT8    3 dB          CQ      0105Z",
      "receiver_callsign": "K9IMM-#",
      "heard_callsign": "KJ5CYH",
      "receiver_region": null,
      "frequency_mhz": 21.074,
      "band": "15m"
    },
    {
      "raw": "DX de K9IMM-#:  21074.00  KS4OT          FT8   -1 dB          CQ      0105Z",
      "receiver_callsign": "K9IMM-#",
      "heard_callsign": "KS4OT",
      "receiver_region": null,
      "frequency_mhz": 21.074,
      "band": "15m"
    },
    {
      "raw": "DX de K9IMM-#:  21074.00  EL2BG          FT8  -18 dB  IJ46    CQ      0105Z",
      "receiver_callsign": "K9IMM-#",
      "heard_callsign": "EL2BG",
      "receiver_region": null,
      "frequency_mhz": 21.074,
      "band": "15m"
    },
    {
      "raw": "DX de K9IMM-#:   7074.00  W8LEW          FT8   14 dB          CQ      0105Z",
      "receiver_callsign": "K9IMM-#",
      "heard_callsign": "W8LEW",
      "receiver_region": null,
      "frequency_mhz": 7.074,
      "band": "40m"
    },
    {
      "raw": "DX de K9IMM-#:   7074.00  M0RUK          FT8   -1 dB          CQ      0105Z",
      "receiver_callsign": "K9IMM-#",
      "heard_callsign": "M0RUK",
      "receiver_region": null,
      "frequency_mhz": 7.074,
      "band": "40m"
    },
    {
      "raw": "DX de K9IMM-#:   7074.00  CT1BFP         FT8   -7 dB          CQ      0105Z",
      "receiver_callsign": "K9IMM-#",
      "heard_callsign": "CT1BFP",
      "receiver_region": null,
      "frequency_mhz": 7.074,
      "band": "40m"
    },
    {
      "raw": "DX de K9IMM-#:   7074.00  LW1DZ          FT8   -8 dB  GF05    CQ      0105Z",
      "receiver_callsign": "K9IMM-#",
      "heard_callsign": "LW1DZ",
      "receiver_region": null,
      "frequency_mhz": 7.074,
      "band": "40m"
    },
    {
      "raw": "DX de K9IMM-#:  10136.00  KB3Z           FT8    4 dB  FN20    CQ      0105Z",
      "receiver_callsign": "K9IMM-#",
      "heard_callsign": "FN20",
      "receiver_region": null,
      "frequency_mhz": 4.0,
      "band": "80m"
    },
    {
      "raw": "DX de K9IMM-#:  14074.00  HK3G           FT8  -12 dB          CQ      0105Z",
      "receiver_callsign": "K9IMM-#",
      "heard_callsign": "HK3G",
      "receiver_region": null,
      "frequency_mhz": 14.074,
      "band": "20m"
    },
    {
      "raw": "DX de K9IMM-#:  14074.00  W5JSS          FT8  -19 dB  EM10    CQ      0105Z",
      "receiver_callsign": "K9IMM-#",
      "heard_callsign": "W5JSS",
      "receiver_region": null,
      "frequency_mhz": 14.074,
      "band": "20m"
    },
    {
      "raw": "DX de K9IMM-#:  14080.00  N5TLH          FT4    7 dB          CQ      0105Z",
      "receiver_callsign": "K9IMM-#",
      "heard_callsign": "N5TLH",
      "receiver_region": null,
      "frequency_mhz": 14.08,
      "band": "20m"
    },
    {
      "raw": "DX de CT1EYQ-#:  5357.00  DK2YCT         FT8    2 dB          CQ      0105Z",
      "receiver_callsign": "CT1EYQ-#",
      "heard_callsign": "0105Z",
      "receiver_region": null,
      "frequency_mhz": 2.0,
      "band": "160m"
    },
    {
      "raw": "DX de CT1EYQ-#:  3573.00  W3DIY          FT8   -8 dB          CQ      0105Z",
      "receiver_callsign": "CT1EYQ-#",
      "heard_callsign": "W3DIY",
      "receiver_region": null,
      "frequency_mhz": 3.573,
      "band": "80m"
    },
    {
      "raw": "DX de LZ4UX-#:  14074.00  F6AOJ          FT8   -7 dB          CQ      0105Z",
      "receiver_callsign": "LZ4UX-#",
      "heard_callsign": "F6AOJ",
      "receiver_region": null,
      "frequency_mhz": 14.074,
      "band": "20m"
    },
    {
      "raw": "DX de LZ4UX-#:  14074.00  IU8RFW         FT8  -21 dB          CQ      0105Z",
      "receiver_callsign": "LZ4UX-#",
      "heard_callsign": "IU8RFW",
      "receiver_region": null,
      "frequency_mhz": 14.074,
      "band": "20m"
    },
    {
      "raw": "DX de WA7LNW-#: 14080.00  N5TLH          FT4   11 dB          CQ      0105Z",
      "receiver_callsign": "WA7LNW-#",
      "heard_callsign": "N5TLH",
      "receiver_region": null,
      "frequency_mhz": 14.08,
      "band": "20m"
    },
    {
      "raw": "DX de WA7LNW-#:  7047.50  NA5M           FT4    3 dB  EM11    CQ      0105Z",
      "receiver_callsign": "WA7LNW-#",
      "heard_callsign": "NA5M",
      "receiver_region": null,
      "frequency_mhz": 7.0475,
      "band": "40m"
    },
    {
      "raw": "DX de WA7LNW-#: 14080.00  WI0P           FT4    0 dB          CQ      0105Z",
      "receiver_callsign": "WA7LNW-#",
      "heard_callsign": "WI0P",
      "receiver_region": null,
      "frequency_mhz": 14.08,
      "band": "20m"
    },
    {
      "raw": "DX de WA7LNW-#: 28074.00  W7YA           FT8  -15 dB          CQ      0105Z",
      "receiver_callsign": "WA7LNW-#",
      "heard_callsign": "W7YA",
      "receiver_region": null,
      "frequency_mhz": 28.074,
      "band": "10m"
    },
    {
      "raw": "DX de KM3T-3-#: 14074.00  S52D           FT8  -13 dB          CQ      0105Z",
      "receiver_callsign": "KM3T-3-#",
      "heard_callsign": "S52D",
      "receiver_region": null,
      "frequency_mhz": 14.074,
      "band": "20m"
    },
    {
      "raw": "DX de W1NT-6-#:  7047.50  NA5M           FT4    5 dB  EM11    CQ      0105Z",
      "receiver_callsign": "W1NT-6-#",
      "heard_callsign": "NA5M",
      "receiver_region": null,
      "frequency_mhz": 7.0475,
      "band": "40m"
    },
    {
      "raw": "DX de W1NT-6-#: 14080.00  WI0P           FT4   -4 dB          CQ      0105Z",
      "receiver_callsign": "W1NT-6-#",
      "heard_callsign": "WI0P",
      "receiver_region": null,
      "frequency_mhz": 14.08,
      "band": "20m"
    },
    {
      "raw": "DX de W1NT-6-#:  3573.00  W3DIY          FT8   20 dB          CQ      0105Z",
      "receiver_callsign": "W1NT-6-#",
      "heard_callsign": "W3DIY",
      "receiver_region": null,
      "frequency_mhz": 3.573,
      "band": "80m"
    },
    {
      "raw": "DX de W1NT-6-#: 21074.00  N5IF           FT8  -15 dB  EM11    CQ      0105Z",
      "receiver_callsign": "W1NT-6-#",
      "heard_callsign": "N5IF",
      "receiver_region": null,
      "frequency_mhz": 21.074,
      "band": "15m"
    },
    {
      "raw": "DX de W1NT-6-#: 18100.00  KA9FOX         FT8   -9 dB  EN43    CQ      0105Z",
      "receiver_callsign": "W1NT-6-#",
      "heard_callsign": "KA9FOX",
      "receiver_region": null,
      "frequency_mhz": 18.1,
      "band": "17m"
    },
    {
      "raw": "DX de W1NT-6-#: 18100.00  HI3K           FT8  -20 dB  FK49    CQ      0105Z",
      "receiver_callsign": "W1NT-6-#",
      "heard_callsign": "HI3K",
      "receiver_region": null,
      "frequency_mhz": 18.1,
      "band": "17m"
    },
    {
      "raw": "DX de N6TV-#:   28074.00  W7YA           FT8  -12 dB          CQ      0105Z",
      "receiver_callsign": "N6TV-#",
      "heard_callsign": "W7YA",
      "receiver_region": null,
      "frequency_mhz": 28.074,
      "band": "10m"
    },
    {
      "raw": "DX de N6TV-#:   21074.00  KW9U           FT8   -9 dB  EN51    CQ      0105Z",
      "receiver_callsign": "N6TV-#",
      "heard_callsign": "KW9U",
      "receiver_region": null,
      "frequency_mhz": 21.074,
      "band": "15m"
    },
    {
      "raw": "DX de WE9V-#:   14080.00  N5TLH          FT4   15 dB          CQ      0105Z",
      "receiver_callsign": "WE9V-#",
      "heard_callsign": "N5TLH",
      "receiver_region": null,
      "frequency_mhz": 14.08,
      "band": "20m"
    },
    {
      "raw": "DX de WE9V-#:   14080.00  WI0P           FT4   13 dB          CQ      0105Z",
      "receiver_callsign": "WE9V-#",
      "heard_callsign": "WI0P",
      "receiver_region": null,
      "frequency_mhz": 14.08,
      "band": "20m"
    },
    {
      "raw": "DX de WE9V-#:   21074.00  N5IF           FT8   -8 dB  EM11    CQ      0105Z",
      "receiver_callsign": "WE9V-#",
      "heard_callsign": "N5IF",
      "receiver_region": null,
      "frequency_mhz": 21.074,
      "band": "15m"
    },
    {
      "raw": "DX de WE9V-#:    7047.50  NA5M           FT4    5 dB  EM11    CQ      0105Z",
      "receiver_callsign": "WE9V-#",
      "heard_callsign": "NA5M",
      "receiver_region": null,
      "frequency_mhz": 7.0475,
      "band": "40m"
    },
    {
      "raw": "DX de WE9V-#:   18100.00  N2SCJ          FT8  -13 dB          CQ      0105Z",
      "receiver_callsign": "WE9V-#",
      "heard_callsign": "N2SCJ",
      "receiver_region": null,
      "frequency_mhz": 18.1,
      "band": "17m"
    },
    {
      "raw": "DX de W2NNN-#:   7074.00  N8CEY          FT8   -4 dB  EM90    CQ      0105Z",
      "receiver_callsign": "W2NNN-#",
      "heard_callsign": "N8CEY",
      "receiver_region": null,
      "frequency_mhz": 7.074,
      "band": "40m"
    },
    {
      "raw": "DX de W2NNN-#:  14080.00  KC3LVG         FT4  -12 dB  FN00    CQ      0105Z",
      "receiver_callsign": "W2NNN-#",
      "heard_callsign": "KC3LVG",
      "receiver_region": null,
      "frequency_mhz": 14.08,
      "band": "20m"
    },
    {
      "raw": "DX de W2NNN-#:  18100.00  KJ5LDV         FT8   -4 dB          CQ      0105Z",
      "receiver_callsign": "W2NNN-#",
      "heard_callsign": "KJ5LDV",
      "receiver_region": null,
      "frequency_mhz": 18.1,
      "band": "17m"
    },
    {
      "raw": "DX de W2NNN-#:  18100.00  N2SCJ          FT8  -17 dB          CQ      0105Z",
      "receiver_callsign": "W2NNN-#",
      "heard_callsign": "N2SCJ",
      "receiver_region": null,
      "frequency_mhz": 18.1,
      "band": "17m"
    },
    {
      "raw": "DX de VE6AO-#:  28074.00  W7YA           FT8  -13 dB          CQ      0105Z",
      "receiver_callsign": "VE6AO-#",
      "heard_callsign": "W7YA",
      "receiver_region": null,
      "frequency_mhz": 28.074,
      "band": "10m"
    },
    {
      "raw": "DX de N2CR-#:    7047.50  NA5M           FT4   -5 dB  EM11    CQ      0105Z",
      "receiver_callsign": "N2CR-#",
      "heard_callsign": "NA5M",
      "receiver_region": null,
      "frequency_mhz": 7.0475,
      "band": "40m"
    },
    {
      "raw": "DX de N2CR-#:    3573.00  W3DIY          FT8    8 dB          CQ      0105Z",
      "receiver_callsign": "N2CR-#",
      "heard_callsign": "W3DIY",
      "receiver_region": null,
      "frequency_mhz": 3.573,
      "band": "80m"
    },
    {
      "raw": "DX de HA8TKS-#:  3573.00  RC6OD          FT8    2 dB  KN87    CQ      0105Z",
      "receiver_callsign": "HA8TKS-#",
      "heard_callsign": "RC6OD",
      "receiver_region": null,
      "frequency_mhz": 3.573,
      "band": "80m"
    },
    {
      "raw": "DX de VU2OY-#:   7074.00  TJ1GD/P        FT8  -13 dB  JJ43    CQ      0105Z",
      "receiver_callsign": "VU2OY-#",
      "heard_callsign": "TJ1GD/P",
      "receiver_region": null,
      "frequency_mhz": 7.074,
      "band": "40m"
    },
    {
      "raw": "DX de VU2OY-#:  14074.00  EA5HM          FT8   -3 dB          CQ      0105Z",
      "receiver_callsign": "VU2OY-#",
      "heard_callsign": "EA5HM",
      "receiver_region": null,
      "frequency_mhz": 14.074,
      "band": "20m"
    }
  ],
  "regions": {
    "Península": {
      "report_count": 0,
      "distinct_receivers": 0,
      "bands": {}
    },
    "Baleares": {
      "report_count": 0,
      "distinct_receivers": 0,
      "bands": {}
    },
    "Canarias": {
      "report_count": 0,
      "distinct_receivers": 0,
      "bands": {}
    }
  },
  "regional_attribution": "Spanish receiver callsign area only; unassigned spots remain global",
  "global_unassigned_spots": 58,
  "quality_gate": {
    "minimum_spots": 5,
    "minimum_distinct_receivers": 3,
    "eligible_for_auxiliary_weight": false
  },
  "limitation": null
}
