{
  "generated_at": "2026-07-19T01:07:43.719451+00:00",
  "validation": {
    "endpoint_located": true,
    "response_received": true,
    "format_parsed": true,
    "current_data_checked": true,
    "local_value_obtained": true
  },
  "errors": [],
  "latest_run": {
    "esfi": 105.360625477255,
    "essn": 56.763542037828,
    "experiment": null,
    "maps": [
      {
        "id": 9281390,
        "ts": 1784422800
      },
      {
        "id": 9281392,
        "ts": 1784426400
      },
      {
        "id": 9281394,
        "ts": 1784430000
      },
      {
        "id": 9281396,
        "ts": 1784433600
      },
      {
        "id": 9281391,
        "ts": 1784437200
      },
      {
        "id": 9281395,
        "ts": 1784440800
      },
      {
        "id": 9281397,
        "ts": 1784444400
      },
      {
        "id": 9281398,
        "ts": 1784448000
      },
      {
        "id": 9281402,
        "ts": 1784451600
      },
      {
        "id": 9281400,
        "ts": 1784455200
      },
      {
        "id": 9281393,
        "ts": 1784458800
      },
      {
        "id": 9281399,
        "ts": 1784462400
      },
      {
        "id": 9281401,
        "ts": 1784466000
      },
      {
        "id": 9281405,
        "ts": 1784469600
      },
      {
        "id": 9281404,
        "ts": 1784473200
      },
      {
        "id": 9281403,
        "ts": 1784476800
      },
      {
        "id": 9281409,
        "ts": 1784480400
      },
      {
        "id": 9281406,
        "ts": 1784484000
      },
      {
        "id": 9281407,
        "ts": 1784487600
      },
      {
        "id": 9281408,
        "ts": 1784491200
      },
      {
        "id": 9281412,
        "ts": 1784494800
      },
      {
        "id": 9281411,
        "ts": 1784498400
      },
      {
        "id": 9281410,
        "ts": 1784502000
      },
      {
        "id": 9281413,
        "ts": 1784505600
      },
      {
        "id": 9281414,
        "ts": 1784509200
      }
    ],
    "run_id": 78389709,
    "target_time": 1784422800
  },
  "available_maps_count": 12,
  "stations_count": 27,
  "hdf5_inventory": {
    "/essn/sfi": {
      "shape": [],
      "dtype": "float32"
    },
    "/essn/ssn": {
      "shape": [],
      "dtype": "float32"
    },
    "/maps/foe": {
      "shape": [
        181,
        361
      ],
      "dtype": "float64"
    },
    "/maps/fof2": {
      "shape": [
        181,
        361
      ],
      "dtype": "float64"
    },
    "/maps/gyf": {
      "shape": [
        181,
        361
      ],
      "dtype": "float64"
    },
    "/maps/hmf2": {
      "shape": [
        181,
        361
      ],
      "dtype": "float64"
    },
    "/maps/md": {
      "shape": [
        181,
        361
      ],
      "dtype": "float64"
    },
    "/maps/mufd": {
      "shape": [
        181,
        361
      ],
      "dtype": "float64"
    },
    "/stationdata/curr": {
      "shape": [],
      "dtype": "object"
    },
    "/stationdata/pred": {
      "shape": [],
      "dtype": "object"
    },
    "/stdev/fof2": {
      "shape": [
        181,
        361
      ],
      "dtype": "float64"
    },
    "/stdev/hmf2": {
      "shape": [
        181,
        361
      ],
      "dtype": "float64"
    },
    "/ts": {
      "shape": [],
      "dtype": "float64"
    }
  },
  "selected_snapshots": [
    {
      "esfi": 105.360625477255,
      "essn": 56.763542037828,
      "filesuffix": "now",
      "run_id": 78389709,
      "start": 1784422800.0,
      "ts": 1784422800.0
    },
    {
      "esfi": 105.241218101387,
      "essn": 56.6017630477432,
      "filesuffix": "now",
      "run_id": 78388534,
      "start": 1784421900.0,
      "ts": 1784421900.0
    },
    {
      "esfi": 104.408430864873,
      "essn": 55.4732863401195,
      "filesuffix": "now",
      "run_id": 78387359,
      "start": 1784421000.0,
      "ts": 1784421000.0
    },
    {
      "esfi": 104.361218070024,
      "essn": 55.4093009665301,
      "filesuffix": "now",
      "run_id": 78386184,
      "start": 1784420100.0,
      "ts": 1784420100.0
    },
    {
      "esfi": 104.291227819688,
      "essn": 55.3144445164366,
      "filesuffix": "now",
      "run_id": 78385009,
      "start": 1784419200.0,
      "ts": 1784419200.0
    }
  ],
  "status": "ok"
}