{
  "generated_at": "2026-07-23T16:49:35.728910+00:00",
  "validation": {
    "endpoint_located": true,
    "response_received": true,
    "format_parsed": true,
    "current_data_checked": true,
    "local_value_obtained": true
  },
  "errors": [],
  "latest_run": {
    "esfi": 110.129460628184,
    "essn": 63.2194430061774,
    "experiment": null,
    "maps": [
      {
        "id": 9341750,
        "ts": 1784825100
      },
      {
        "id": 9341752,
        "ts": 1784828700
      },
      {
        "id": 9341751,
        "ts": 1784832300
      },
      {
        "id": 9341743,
        "ts": 1784835900
      },
      {
        "id": 9341740,
        "ts": 1784839500
      },
      {
        "id": 9341749,
        "ts": 1784843100
      },
      {
        "id": 9341747,
        "ts": 1784846700
      },
      {
        "id": 9341742,
        "ts": 1784850300
      },
      {
        "id": 9341753,
        "ts": 1784853900
      },
      {
        "id": 9341755,
        "ts": 1784857500
      },
      {
        "id": 9341744,
        "ts": 1784861100
      },
      {
        "id": 9341746,
        "ts": 1784864700
      },
      {
        "id": 9341748,
        "ts": 1784868300
      },
      {
        "id": 9341754,
        "ts": 1784871900
      },
      {
        "id": 9341745,
        "ts": 1784875500
      },
      {
        "id": 9341757,
        "ts": 1784879100
      },
      {
        "id": 9341756,
        "ts": 1784882700
      },
      {
        "id": 9341758,
        "ts": 1784886300
      },
      {
        "id": 9341760,
        "ts": 1784889900
      },
      {
        "id": 9341759,
        "ts": 1784893500
      },
      {
        "id": 9341741,
        "ts": 1784897100
      },
      {
        "id": 9341761,
        "ts": 1784900700
      },
      {
        "id": 9341762,
        "ts": 1784904300
      },
      {
        "id": 9341763,
        "ts": 1784907900
      },
      {
        "id": 9341764,
        "ts": 1784911500
      }
    ],
    "run_id": 78874861,
    "target_time": 1784825100
  },
  "available_maps_count": 12,
  "stations_count": 26,
  "hdf5_inventory": {
    "/essn/sfi": {
      "shape": [],
      "dtype": "float32"
    },
    "/essn/ssn": {
      "shape": [],
      "dtype": "float32"
    },
    "/maps/foe": {
      "shape": [
        181,
        361
      ],
      "dtype": "float64"
    },
    "/maps/fof2": {
      "shape": [
        181,
        361
      ],
      "dtype": "float64"
    },
    "/maps/gyf": {
      "shape": [
        181,
        361
      ],
      "dtype": "float64"
    },
    "/maps/hmf2": {
      "shape": [
        181,
        361
      ],
      "dtype": "float64"
    },
    "/maps/md": {
      "shape": [
        181,
        361
      ],
      "dtype": "float64"
    },
    "/maps/mufd": {
      "shape": [
        181,
        361
      ],
      "dtype": "float64"
    },
    "/stationdata/curr": {
      "shape": [],
      "dtype": "object"
    },
    "/stationdata/pred": {
      "shape": [],
      "dtype": "object"
    },
    "/stdev/fof2": {
      "shape": [
        181,
        361
      ],
      "dtype": "float64"
    },
    "/stdev/hmf2": {
      "shape": [
        181,
        361
      ],
      "dtype": "float64"
    },
    "/ts": {
      "shape": [],
      "dtype": "float64"
    }
  },
  "selected_snapshots": [
    {
      "esfi": 110.129460628184,
      "essn": 63.2194430061774,
      "filesuffix": "now",
      "run_id": 78874861,
      "start": 1784825100.0,
      "ts": 1784825100.0
    },
    {
      "esfi": 110.222546489099,
      "essn": 63.345359900869,
      "filesuffix": "now",
      "run_id": 78873680,
      "start": 1784824200.0,
      "ts": 1784824200.0
    },
    {
      "esfi": 110.476038255208,
      "essn": 63.6882379100656,
      "filesuffix": "now",
      "run_id": 78872499,
      "start": 1784823300.0,
      "ts": 1784823300.0
    },
    {
      "esfi": 110.549498242408,
      "essn": 63.7875960615408,
      "filesuffix": "now",
      "run_id": 78871318,
      "start": 1784822400.0,
      "ts": 1784822400.0
    },
    {
      "esfi": 110.852490523936,
      "essn": 64.197382520379,
      "filesuffix": "now",
      "run_id": 78870137,
      "start": 1784821500.0,
      "ts": 1784821500.0
    }
  ],
  "status": "ok"
}