{
  "generated_at": "2026-07-23T11:45:42.666764+00:00",
  "validation": {
    "endpoint_located": true,
    "response_received": true,
    "format_parsed": true,
    "current_data_checked": true,
    "local_value_obtained": true
  },
  "errors": [],
  "latest_run": {
    "esfi": 113.439330136008,
    "essn": 67.6943481204733,
    "experiment": null,
    "maps": [
      {
        "id": 9338743,
        "ts": 1784807100
      },
      {
        "id": 9338751,
        "ts": 1784810700
      },
      {
        "id": 9338749,
        "ts": 1784814300
      },
      {
        "id": 9338746,
        "ts": 1784817900
      },
      {
        "id": 9338745,
        "ts": 1784821500
      },
      {
        "id": 9338744,
        "ts": 1784825100
      },
      {
        "id": 9338750,
        "ts": 1784828700
      },
      {
        "id": 9338740,
        "ts": 1784832300
      },
      {
        "id": 9338742,
        "ts": 1784835900
      },
      {
        "id": 9338748,
        "ts": 1784839500
      },
      {
        "id": 9338747,
        "ts": 1784843100
      },
      {
        "id": 9338759,
        "ts": 1784846700
      },
      {
        "id": 9338755,
        "ts": 1784850300
      },
      {
        "id": 9338752,
        "ts": 1784853900
      },
      {
        "id": 9338754,
        "ts": 1784857500
      },
      {
        "id": 9338753,
        "ts": 1784861100
      },
      {
        "id": 9338760,
        "ts": 1784864700
      },
      {
        "id": 9338756,
        "ts": 1784868300
      },
      {
        "id": 9338758,
        "ts": 1784871900
      },
      {
        "id": 9338757,
        "ts": 1784875500
      },
      {
        "id": 9338762,
        "ts": 1784879100
      },
      {
        "id": 9338761,
        "ts": 1784882700
      },
      {
        "id": 9338764,
        "ts": 1784886300
      },
      {
        "id": 9338763,
        "ts": 1784889900
      },
      {
        "id": 9338741,
        "ts": 1784893500
      }
    ],
    "run_id": 78851241,
    "target_time": 1784807100
  },
  "available_maps_count": 12,
  "stations_count": 25,
  "hdf5_inventory": {
    "/essn/sfi": {
      "shape": [],
      "dtype": "float32"
    },
    "/essn/ssn": {
      "shape": [],
      "dtype": "float32"
    },
    "/maps/foe": {
      "shape": [
        181,
        361
      ],
      "dtype": "float64"
    },
    "/maps/fof2": {
      "shape": [
        181,
        361
      ],
      "dtype": "float64"
    },
    "/maps/gyf": {
      "shape": [
        181,
        361
      ],
      "dtype": "float64"
    },
    "/maps/hmf2": {
      "shape": [
        181,
        361
      ],
      "dtype": "float64"
    },
    "/maps/md": {
      "shape": [
        181,
        361
      ],
      "dtype": "float64"
    },
    "/maps/mufd": {
      "shape": [
        181,
        361
      ],
      "dtype": "float64"
    },
    "/stationdata/curr": {
      "shape": [],
      "dtype": "object"
    },
    "/stationdata/pred": {
      "shape": [],
      "dtype": "object"
    },
    "/stdev/fof2": {
      "shape": [
        181,
        361
      ],
      "dtype": "float64"
    },
    "/stdev/hmf2": {
      "shape": [
        181,
        361
      ],
      "dtype": "float64"
    },
    "/ts": {
      "shape": [],
      "dtype": "float64"
    }
  },
  "selected_snapshots": [
    {
      "esfi": 113.439330136008,
      "essn": 67.6943481204733,
      "filesuffix": "now",
      "run_id": 78851241,
      "start": 1784807100.0,
      "ts": 1784807100.0
    },
    {
      "esfi": 113.479993233176,
      "essn": 67.7492942062518,
      "filesuffix": "now",
      "run_id": 78850060,
      "start": 1784806200.0,
      "ts": 1784806200.0
    },
    {
      "esfi": 113.457784772974,
      "essn": 67.7192850730385,
      "filesuffix": "now",
      "run_id": 78848879,
      "start": 1784805300.0,
      "ts": 1784805300.0
    },
    {
      "esfi": 113.514839215481,
      "essn": 67.7963793269844,
      "filesuffix": "now",
      "run_id": 78847698,
      "start": 1784804400.0,
      "ts": 1784804400.0
    },
    {
      "esfi": 113.420508876842,
      "essn": 67.6689156131313,
      "filesuffix": "now",
      "run_id": 78846517,
      "start": 1784803500.0,
      "ts": 1784803500.0
    }
  ],
  "status": "ok"
}