{
  "generated_at": "2026-07-22T00:52:37.502809+00:00",
  "validation": {
    "endpoint_located": true,
    "response_received": true,
    "format_parsed": true,
    "current_data_checked": true,
    "local_value_obtained": true
  },
  "errors": [],
  "latest_run": {
    "esfi": 111.06145420086,
    "essn": 64.4799750300158,
    "experiment": null,
    "maps": [
      {
        "id": 9317741,
        "ts": 1784681100
      },
      {
        "id": 9317746,
        "ts": 1784684700
      },
      {
        "id": 9317747,
        "ts": 1784688300
      },
      {
        "id": 9317749,
        "ts": 1784691900
      },
      {
        "id": 9317748,
        "ts": 1784695500
      },
      {
        "id": 9317745,
        "ts": 1784699100
      },
      {
        "id": 9317742,
        "ts": 1784702700
      },
      {
        "id": 9317750,
        "ts": 1784706300
      },
      {
        "id": 9317751,
        "ts": 1784709900
      },
      {
        "id": 9317752,
        "ts": 1784713500
      },
      {
        "id": 9317743,
        "ts": 1784717100
      },
      {
        "id": 9317744,
        "ts": 1784720700
      },
      {
        "id": 9317754,
        "ts": 1784724300
      },
      {
        "id": 9317753,
        "ts": 1784727900
      },
      {
        "id": 9317756,
        "ts": 1784731500
      },
      {
        "id": 9317758,
        "ts": 1784735100
      },
      {
        "id": 9317740,
        "ts": 1784738700
      },
      {
        "id": 9317757,
        "ts": 1784742300
      },
      {
        "id": 9317755,
        "ts": 1784745900
      },
      {
        "id": 9317760,
        "ts": 1784749500
      },
      {
        "id": 9317763,
        "ts": 1784753100
      },
      {
        "id": 9317764,
        "ts": 1784756700
      },
      {
        "id": 9317759,
        "ts": 1784760300
      },
      {
        "id": 9317762,
        "ts": 1784763900
      },
      {
        "id": 9317761,
        "ts": 1784767500
      }
    ],
    "run_id": 78685901,
    "target_time": 1784681100
  },
  "available_maps_count": 12,
  "stations_count": 25,
  "hdf5_inventory": {
    "/essn/sfi": {
      "shape": [],
      "dtype": "float32"
    },
    "/essn/ssn": {
      "shape": [],
      "dtype": "float32"
    },
    "/maps/foe": {
      "shape": [
        181,
        361
      ],
      "dtype": "float64"
    },
    "/maps/fof2": {
      "shape": [
        181,
        361
      ],
      "dtype": "float64"
    },
    "/maps/gyf": {
      "shape": [
        181,
        361
      ],
      "dtype": "float64"
    },
    "/maps/hmf2": {
      "shape": [
        181,
        361
      ],
      "dtype": "float64"
    },
    "/maps/md": {
      "shape": [
        181,
        361
      ],
      "dtype": "float64"
    },
    "/maps/mufd": {
      "shape": [
        181,
        361
      ],
      "dtype": "float64"
    },
    "/stationdata/curr": {
      "shape": [],
      "dtype": "object"
    },
    "/stationdata/pred": {
      "shape": [],
      "dtype": "object"
    },
    "/stdev/fof2": {
      "shape": [
        181,
        361
      ],
      "dtype": "float64"
    },
    "/stdev/hmf2": {
      "shape": [
        181,
        361
      ],
      "dtype": "float64"
    },
    "/ts": {
      "shape": [],
      "dtype": "float64"
    }
  },
  "selected_snapshots": [
    {
      "esfi": 111.06145420086,
      "essn": 64.4799750300158,
      "filesuffix": "now",
      "run_id": 78685901,
      "start": 1784681100.0,
      "ts": 1784681100.0
    },
    {
      "esfi": 111.14592787817,
      "essn": 64.5942077460899,
      "filesuffix": "now",
      "run_id": 78684720,
      "start": 1784680200.0,
      "ts": 1784680200.0
    },
    {
      "esfi": 111.315153766818,
      "essn": 64.8230403880764,
      "filesuffix": "now",
      "run_id": 78683539,
      "start": 1784679300.0,
      "ts": 1784679300.0
    },
    {
      "esfi": 111.437253280525,
      "essn": 64.9881394161535,
      "filesuffix": "now",
      "run_id": 78682358,
      "start": 1784678400.0,
      "ts": 1784678400.0
    },
    {
      "esfi": 111.515671305822,
      "essn": 65.0941702834971,
      "filesuffix": "now",
      "run_id": 78681177,
      "start": 1784677500.0,
      "ts": 1784677500.0
    }
  ],
  "status": "ok"
}