{
  "generated_at": "2026-07-20T13:20:38.484753+00:00",
  "validation": {
    "endpoint_located": true,
    "response_received": true,
    "format_parsed": true,
    "current_data_checked": true,
    "local_value_obtained": true
  },
  "errors": [],
  "latest_run": {
    "esfi": 112.424307248273,
    "essn": 66.3225611805697,
    "experiment": null,
    "maps": [
      {
        "id": 9303146,
        "ts": 1784553300
      },
      {
        "id": 9303150,
        "ts": 1784556900
      },
      {
        "id": 9303147,
        "ts": 1784560500
      },
      {
        "id": 9303152,
        "ts": 1784564100
      },
      {
        "id": 9303145,
        "ts": 1784567700
      },
      {
        "id": 9303143,
        "ts": 1784571300
      },
      {
        "id": 9303148,
        "ts": 1784574900
      },
      {
        "id": 9303144,
        "ts": 1784578500
      },
      {
        "id": 9303151,
        "ts": 1784582100
      },
      {
        "id": 9303142,
        "ts": 1784585700
      },
      {
        "id": 9303149,
        "ts": 1784589300
      },
      {
        "id": 9303153,
        "ts": 1784592900
      },
      {
        "id": 9303154,
        "ts": 1784596500
      },
      {
        "id": 9303141,
        "ts": 1784600100
      },
      {
        "id": 9303158,
        "ts": 1784603700
      },
      {
        "id": 9303156,
        "ts": 1784607300
      },
      {
        "id": 9303155,
        "ts": 1784610900
      },
      {
        "id": 9303157,
        "ts": 1784614500
      },
      {
        "id": 9303162,
        "ts": 1784618100
      },
      {
        "id": 9303159,
        "ts": 1784621700
      },
      {
        "id": 9303160,
        "ts": 1784625300
      },
      {
        "id": 9303161,
        "ts": 1784628900
      },
      {
        "id": 9303163,
        "ts": 1784632500
      },
      {
        "id": 9303164,
        "ts": 1784636100
      },
      {
        "id": 9303140,
        "ts": 1784639700
      }
    ],
    "run_id": 78560084,
    "target_time": 1784553300
  },
  "available_maps_count": 12,
  "stations_count": 26,
  "hdf5_inventory": {
    "/essn/sfi": {
      "shape": [],
      "dtype": "float32"
    },
    "/essn/ssn": {
      "shape": [],
      "dtype": "float32"
    },
    "/maps/foe": {
      "shape": [
        181,
        361
      ],
      "dtype": "float64"
    },
    "/maps/fof2": {
      "shape": [
        181,
        361
      ],
      "dtype": "float64"
    },
    "/maps/gyf": {
      "shape": [
        181,
        361
      ],
      "dtype": "float64"
    },
    "/maps/hmf2": {
      "shape": [
        181,
        361
      ],
      "dtype": "float64"
    },
    "/maps/md": {
      "shape": [
        181,
        361
      ],
      "dtype": "float64"
    },
    "/maps/mufd": {
      "shape": [
        181,
        361
      ],
      "dtype": "float64"
    },
    "/stationdata/curr": {
      "shape": [],
      "dtype": "object"
    },
    "/stationdata/pred": {
      "shape": [],
      "dtype": "object"
    },
    "/stdev/fof2": {
      "shape": [
        181,
        361
      ],
      "dtype": "float64"
    },
    "/stdev/hmf2": {
      "shape": [
        181,
        361
      ],
      "dtype": "float64"
    },
    "/ts": {
      "shape": [],
      "dtype": "float64"
    }
  },
  "selected_snapshots": [
    {
      "esfi": 112.424307248273,
      "essn": 66.3225611805697,
      "filesuffix": "now",
      "run_id": 78560084,
      "start": 1784553300.0,
      "ts": 1784553300.0
    },
    {
      "esfi": 112.368931871198,
      "essn": 66.2477092336452,
      "filesuffix": "now",
      "run_id": 78558909,
      "start": 1784552400.0,
      "ts": 1784552400.0
    },
    {
      "esfi": 112.316840164542,
      "essn": 66.1772946557072,
      "filesuffix": "now",
      "run_id": 78557734,
      "start": 1784551500.0,
      "ts": 1784551500.0
    },
    {
      "esfi": 112.257314606464,
      "essn": 66.096829963712,
      "filesuffix": "now",
      "run_id": 78556559,
      "start": 1784550600.0,
      "ts": 1784550600.0
    },
    {
      "esfi": 112.162235462263,
      "essn": 65.9683018715003,
      "filesuffix": "now",
      "run_id": 78555384,
      "start": 1784549700.0,
      "ts": 1784549700.0
    }
  ],
  "status": "ok"
}